virtualenv_bb/__init__.py
virtualenv_bb/activate
virtualenv_better_bash-0.3.2.dist-info/LICENSE
virtualenv_better_bash-0.3.2.dist-info/METADATA
virtualenv_better_bash-0.3.2.dist-info/WHEEL
virtualenv_better_bash-0.3.2.dist-info/entry_points.txt
virtualenv_better_bash-0.3.2.dist-info/top_level.txt
virtualenv_better_bash-0.3.2.dist-info/RECORD
